aws_list_all/__init__.py
aws_list_all/__main__.py
aws_list_all/client.py
aws_list_all/endpoint_hosts.json
aws_list_all/introspection.py
aws_list_all/listing.py
aws_list_all/query.py
aws_list_all/service_regions.json
aws_list_all/test_introspection.py
aws_list_all-0.9.2.dist-info/LICENSE
aws_list_all-0.9.2.dist-info/METADATA
aws_list_all-0.9.2.dist-info/WHEEL
aws_list_all-0.9.2.dist-info/entry_points.txt
aws_list_all-0.9.2.dist-info/top_level.txt
aws_list_all-0.9.2.dist-info/RECORD
