Metadata-Version: 2.1
Name: aws-list-all
Version: 0.9.2
Summary: List all your AWS resources, all regions, all services.
Home-page: https://github.com/JohannesEbke/aws_list_all
Author: Johannes Ebke
Author-email: johannes@ebke.org
Keywords: aws boto3 listings resources region services
Classifier: Development Status :: 4 - Beta
Classifier: Environment :: Console
Classifier: Intended Audience :: Developers
Classifier: License :: OSI Approved :: MIT License
Classifier: Natural Language :: English
Classifier: Programming Language :: Python :: 3
Classifier: Programming Language :: Python :: 3.7
Classifier: Programming Language :: Python :: 3.11
License-File: LICENSE
Requires-Dist: app-json-file-cache (>=0.2.2)
Requires-Dist: boto3 (>=1.26.7)
